{"term": "hotels", "name": "Royale Travels", "location": {"country": "AU", "address2": null, "state": "ACT", "city": "Phillip", "address1": "48 Colbee Crt", "zip_code": "2606", "address3": null}, "id": "royale-travels-phillip", "phone": "+61262827448", "is_closed": false, "coordinates": {"latitude": -35.3528709, "longitude": 149.0873108}, "review_count": 0, "rating": 0.0, "image_url": "", "url": "https://www.yelp.com/biz/royale-travels-phillip?adjust_creative=92p07_JjKyriZTQxAXRiKQ&utm_campaign=yelp_api_v3&utm_medium=api_v3_business_lookup&utm_source=92p07_JjKyriZTQxAXRiKQ", "is_claimed": false, "categories": [{"alias": "travelservices", "title": "Travel Services"}], "photos": []}