{"term": "restaurants", "name": "Borek Bakehouse", "location": {"country": "AU", "address2": "", "state": "VIC", "city": "Melbourne", "address1": "481 Elizabeth St", "zip_code": "3000", "address3": ""}, "id": "borek-bakehouse-melbourne", "phone": "+61393295553", "hours": [{"is_open_now": true, "open": [{"start": "0800", "end": "1730", "is_overnight": false, "day": 0}, {"start": "0800", "end": "1730", "is_overnight": false, "day": 1}, {"start": "0800", "end": "1730", "is_overnight": false, "day": 2}, {"start": "0800", "end": "1730", "is_overnight": false, "day": 3}, {"start": "0800", "end": "1730", "is_overnight": false, "day": 4}, {"start": "0800", "end": "1730", "is_overnight": false, "day": 5}, {"start": "0800", "end": "1730", "is_overnight": false, "day": 6}], "hours_type": "REGULAR"}], "is_closed": false, "coordinates": {"latitude": -37.8078, "longitude": 144.9599}, "price": "$", "review_count": 6, "rating": 4.5, "image_url": "https://s3-media2.fl.yelpcdn.com/bphoto/Ch2V-I0pPN2gxXZx79FbVA/o.jpg", "url": "https://www.yelp.com/biz/borek-bakehouse-melbourne?adjust_creative=92p07_JjKyriZTQxAXRiKQ&utm_campaign=yelp_api_v3&utm_medium=api_v3_business_lookup&utm_source=92p07_JjKyriZTQxAXRiKQ", "is_claimed": false, "categories": [{"alias": "bakeries", "title": "Bakeries"}, {"alias": "turkish", "title": "Turkish"}], "photos": ["https://s3-media3.fl.yelpcdn.com/bphoto/Ch2V-I0pPN2gxXZx79FbVA/o.jpg", "https://s3-media4.fl.yelpcdn.com/bphoto/1BHB0dtpGTlzJN6AJI9oVQ/o.jpg", "https://s3-media3.fl.yelpcdn.com/bphoto/U2P24El8D3CJUqYV3evgxg/o.jpg"]}