{"term": "restaurants", "name": "Nick The Greek", "location": {"country": "US", "address2": "", "state": "CA", "city": "San Jose", "address1": "143 W Santa Clara St", "zip_code": "95113", "address3": ""}, "id": "nick-the-greek-san-jose", "phone": "+14082946425", "hours": [{"is_open_now": true, "open": [{"start": "1100", "end": "2300", "is_overnight": false, "day": 0}, {"start": "1100", "end": "2300", "is_overnight": false, "day": 1}, {"start": "1100", "end": "2300", "is_overnight": false, "day": 2}, {"start": "1100", "end": "2300", "is_overnight": false, "day": 3}, {"start": "1100", "end": "0300", "is_overnight": true, "day": 4}, {"start": "1100", "end": "0300", "is_overnight": true, "day": 5}, {"start": "1100", "end": "2300", "is_overnight": false, "day": 6}], "hours_type": "REGULAR"}], "is_closed": false, "coordinates": {"latitude": 37.335210678353, "longitude": -121.892775829557}, "review_count": 504, "price": "$", "rating": 4.0, "image_url": "https://s3-media2.fl.yelpcdn.com/bphoto/hGUTqcye4dCCcrifXThxtQ/o.jpg", "url": "https://www.yelp.com/biz/nick-the-greek-san-jose?adjust_creative=92p07_JjKyriZTQxAXRiKQ&utm_campaign=yelp_api_v3&utm_medium=api_v3_business_lookup&utm_source=92p07_JjKyriZTQxAXRiKQ", "is_claimed": true, "categories": [{"alias": "greek", "title": "Greek"}], "photos": ["https://s3-media1.fl.yelpcdn.com/bphoto/hGUTqcye4dCCcrifXThxtQ/o.jpg", "https://s3-media2.fl.yelpcdn.com/bphoto/BLNkgAJQPdHcH_Xem8RKhQ/o.jpg", "https://s3-media2.fl.yelpcdn.com/bphoto/4BXPFOZbHwcuKDVsoLjWLg/o.jpg"]}