{"term": "attractions", "name": "Art In The Heart @ The Rocks", "location": {"country": "AU", "address2": "", "state": "NSW", "city": "The Rocks", "address1": "75 George Street", "zip_code": "2000", "address3": ""}, "id": "art-in-the-heart-the-rocks-the-rocks", "phone": "", "hours": [{"is_open_now": true, "open": [{"start": "1100", "end": "1900", "is_overnight": false, "day": 0}, {"start": "1100", "end": "1900", "is_overnight": false, "day": 1}, {"start": "1100", "end": "1900", "is_overnight": false, "day": 2}, {"start": "1100", "end": "1900", "is_overnight": false, "day": 3}, {"start": "1100", "end": "1900", "is_overnight": false, "day": 4}, {"start": "1000", "end": "1900", "is_overnight": false, "day": 5}, {"start": "1000", "end": "1900", "is_overnight": false, "day": 6}], "hours_type": "REGULAR"}], "is_closed": false, "coordinates": {"latitude": -33.8586884, "longitude": 151.2087555}, "review_count": 1, "rating": 4.0, "image_url": "https://s3-media1.fl.yelpcdn.com/bphoto/Pyi1fb56mIlPj8vIsmUT_g/o.jpg", "url": "https://www.yelp.com/biz/art-in-the-heart-the-rocks-the-rocks?adjust_creative=92p07_JjKyriZTQxAXRiKQ&utm_campaign=yelp_api_v3&utm_medium=api_v3_business_lookup&utm_source=92p07_JjKyriZTQxAXRiKQ", "is_claimed": false, "categories": [{"alias": "galleries", "title": "Art Galleries"}], "photos": ["https://s3-media4.fl.yelpcdn.com/bphoto/Pyi1fb56mIlPj8vIsmUT_g/o.jpg"]}