{"term": "restaurants", "name": "The Kitchen", "phone": "+17023641441", "id": "the-kitchen-las-vegas", "hours": [{"is_open_now": false, "open": [{"start": "0800", "end": "1500", "is_overnight": false, "day": 0}, {"start": "0800", "end": "1500", "is_overnight": false, "day": 1}, {"start": "0800", "end": "1500", "is_overnight": false, "day": 2}, {"start": "0800", "end": "1500", "is_overnight": false, "day": 3}, {"start": "0800", "end": "1500", "is_overnight": false, "day": 4}], "hours_type": "REGULAR"}], "is_closed": false, "coordinates": {"latitude": 36.08167, "longitude": -115.21183}, "price": "$", "review_count": 15, "rating": 4.5, "image_url": "https://s3-media3.fl.yelpcdn.com/bphoto/R4cN40RZAn8HkiBVpFG_5g/o.jpg", "url": "https://www.yelp.com/biz/the-kitchen-las-vegas?adjust_creative=92p07_JjKyriZTQxAXRiKQ&utm_campaign=yelp_api_v3&utm_medium=api_v3_business_lookup&utm_source=92p07_JjKyriZTQxAXRiKQ", "is_claimed": true, "categories": [{"alias": "sandwiches", "title": "Sandwiches"}], "photos": ["https://s3-media3.fl.yelpcdn.com/bphoto/R4cN40RZAn8HkiBVpFG_5g/o.jpg", "https://s3-media4.fl.yelpcdn.com/bphoto/j_4awqCgqAMYe1Hm77A-rw/o.jpg", "https://s3-media4.fl.yelpcdn.com/bphoto/lF1fAsSKcxsj3yxophVdcQ/o.jpg"], "location": {"country": "US", "address2": null, "state": "NV", "city": "Las Vegas", "address1": "5165 W Oquendo Rd", "zip_code": "89118", "address3": null}}