{"term": "restaurants", "name": "Sound & Fog", "location": {"country": "US", "address2": "", "state": "WA", "city": "Seattle", "address1": "4735 40th Ave SW", "zip_code": "98116", "address3": null}, "id": "sound-and-fog-seattle", "phone": "+12066181444", "hours": [{"is_open_now": false, "open": [{"start": "0630", "end": "1900", "is_overnight": false, "day": 0}, {"start": "0630", "end": "1900", "is_overnight": false, "day": 1}, {"start": "0630", "end": "1900", "is_overnight": false, "day": 2}, {"start": "0630", "end": "2000", "is_overnight": false, "day": 3}, {"start": "0630", "end": "2100", "is_overnight": false, "day": 4}, {"start": "0800", "end": "2100", "is_overnight": false, "day": 5}, {"start": "0800", "end": "1900", "is_overnight": false, "day": 6}], "hours_type": "REGULAR"}], "is_closed": false, "coordinates": {"latitude": 47.55994, "longitude": -122.38326}, "price": "$", "review_count": 36, "rating": 5.0, "image_url": "https://s3-media4.fl.yelpcdn.com/bphoto/ySZbFCYKp9mub6_uWiGlyg/o.jpg", "url": "https://www.yelp.com/biz/sound-and-fog-seattle?adjust_creative=92p07_JjKyriZTQxAXRiKQ&utm_campaign=yelp_api_v3&utm_medium=api_v3_business_lookup&utm_source=92p07_JjKyriZTQxAXRiKQ", "is_claimed": true, "categories": [{"alias": "bars", "title": "Bars"}, {"alias": "cafes", "title": "Cafes"}, {"alias": "coffee", "title": "Coffee & Tea"}], "photos": ["https://s3-media2.fl.yelpcdn.com/bphoto/ySZbFCYKp9mub6_uWiGlyg/o.jpg", "https://s3-media1.fl.yelpcdn.com/bphoto/pT5RXXaqSB6adB6DQyIhZQ/o.jpg", "https://s3-media3.fl.yelpcdn.com/bphoto/2tqvCUHTqAMNxBZyR3wmDQ/o.jpg"]}