{"term": "attractions", "name": "Stockport Air raid Shelters", "location": {"country": "GB", "address2": "Stockport", "state": "MAN", "city": "Manchester", "address1": "Merseyway", "zip_code": "SK3 9QW", "address3": ""}, "id": "stockport-air-raid-shelters-manchester", "phone": "", "is_closed": false, "coordinates": {"latitude": 53.4116096, "longitude": -2.1596401}, "review_count": 3, "rating": 4.0, "image_url": "", "url": "https://www.yelp.com/biz/stockport-air-raid-shelters-manchester?adjust_creative=92p07_JjKyriZTQxAXRiKQ&utm_campaign=yelp_api_v3&utm_medium=api_v3_business_lookup&utm_source=92p07_JjKyriZTQxAXRiKQ", "is_claimed": false, "categories": [{"alias": "museums", "title": "Museums"}], "photos": []}