{"term": "restaurants", "name": "Nittaya's Secret Kitchen", "phone": "+17023608885", "id": "nittayas-secret-kitchen-las-vegas", "hours": [{"is_open_now": true, "open": [{"start": "1100", "end": "2200", "is_overnight": false, "day": 0}, {"start": "1100", "end": "2200", "is_overnight": false, "day": 1}, {"start": "1100", "end": "2200", "is_overnight": false, "day": 2}, {"start": "1100", "end": "2200", "is_overnight": false, "day": 3}, {"start": "1100", "end": "2200", "is_overnight": false, "day": 4}, {"start": "1100", "end": "2200", "is_overnight": false, "day": 5}, {"start": "1600", "end": "2130", "is_overnight": false, "day": 6}], "hours_type": "REGULAR"}], "is_closed": false, "coordinates": {"latitude": 36.19829, "longitude": -115.28282}, "review_count": 392, "price": "$$", "rating": 4.5, "image_url": "https://s3-media3.fl.yelpcdn.com/bphoto/nd4JZAiQUQYDg1qXFaHwzQ/o.jpg", "url": "https://www.yelp.com/biz/nittayas-secret-kitchen-las-vegas?adjust_creative=92p07_JjKyriZTQxAXRiKQ&utm_campaign=yelp_api_v3&utm_medium=api_v3_business_lookup&utm_source=92p07_JjKyriZTQxAXRiKQ", "is_claimed": true, "categories": [{"alias": "thai", "title": "Thai"}], "photos": ["https://s3-media3.fl.yelpcdn.com/bphoto/nd4JZAiQUQYDg1qXFaHwzQ/o.jpg", "https://s3-media3.fl.yelpcdn.com/bphoto/gaXpVBL1zY9z5J3zQ1Rxjw/o.jpg", "https://s3-media2.fl.yelpcdn.com/bphoto/JIF7G14sFSJcQnMuVTP3YQ/o.jpg"], "location": {"country": "US", "address2": "Ste 110", "state": "NV", "city": "Las Vegas", "address1": "2110 N Rampart", "zip_code": "89128", "address3": ""}}