{"term": "restaurants", "name": "Pampa Grill & Market", "location": {"country": "US", "address2": "", "state": "TX", "city": "Houston", "address1": "10111 Hammerly Blvd", "zip_code": "77080", "address3": ""}, "id": "pampa-grill-and-market-houston-2", "phone": "+17137220666", "hours": [{"is_open_now": false, "open": [{"start": "1100", "end": "2100", "is_overnight": false, "day": 1}, {"start": "1100", "end": "2100", "is_overnight": false, "day": 2}, {"start": "1100", "end": "2100", "is_overnight": false, "day": 3}, {"start": "1100", "end": "2200", "is_overnight": false, "day": 4}, {"start": "1200", "end": "2200", "is_overnight": false, "day": 5}, {"start": "1200", "end": "1800", "is_overnight": false, "day": 6}], "hours_type": "REGULAR"}], "is_closed": false, "coordinates": {"latitude": 29.8125151, "longitude": -95.5429566}, "price": "$$", "review_count": 84, "rating": 4.5, "image_url": "https://s3-media4.fl.yelpcdn.com/bphoto/IqZxBZXJqfOke_4HmdGwrg/o.jpg", "url": "https://www.yelp.com/biz/pampa-grill-and-market-houston-2?adjust_creative=92p07_JjKyriZTQxAXRiKQ&utm_campaign=yelp_api_v3&utm_medium=api_v3_business_lookup&utm_source=92p07_JjKyriZTQxAXRiKQ", "is_claimed": true, "categories": [{"alias": "argentine", "title": "Argentine"}, {"alias": "latin", "title": "Latin American"}], "photos": ["https://s3-media3.fl.yelpcdn.com/bphoto/IqZxBZXJqfOke_4HmdGwrg/o.jpg", "https://s3-media1.fl.yelpcdn.com/bphoto/34gnw7qng3yxpMzu4yx6SA/o.jpg", "https://s3-media1.fl.yelpcdn.com/bphoto/HWZsmTFObPbIJI4tr1urYQ/o.jpg"]}