{"term": "attractions", "name": "Hard Rock Cafe", "phone": "+12123433355", "id": "hard-rock-cafe-new-york-10", "hours": [{"is_open_now": false, "open": [{"start": "1100", "end": "0030", "is_overnight": true, "day": 0}, {"start": "1100", "end": "0030", "is_overnight": true, "day": 1}, {"start": "1100", "end": "0030", "is_overnight": true, "day": 2}, {"start": "1100", "end": "0030", "is_overnight": true, "day": 3}, {"start": "1100", "end": "0130", "is_overnight": true, "day": 4}, {"start": "1100", "end": "0130", "is_overnight": true, "day": 5}, {"start": "1100", "end": "0030", "is_overnight": true, "day": 6}], "hours_type": "REGULAR"}], "is_closed": false, "coordinates": {"latitude": 40.7568933348604, "longitude": -73.9865529930391}, "review_count": 547, "price": "$$", "rating": 3.5, "image_url": "https://s3-media2.fl.yelpcdn.com/bphoto/DA3a1utmWOOTuuHTHgSZ9A/o.jpg", "url": "https://www.yelp.com/biz/hard-rock-cafe-new-york-10?adjust_creative=92p07_JjKyriZTQxAXRiKQ&utm_campaign=yelp_api_v3&utm_medium=api_v3_business_lookup&utm_source=92p07_JjKyriZTQxAXRiKQ", "is_claimed": true, "categories": [{"alias": "newamerican", "title": "American (New)"}, {"alias": "burgers", "title": "Burgers"}, {"alias": "musicvenues", "title": "Music Venues"}], "photos": ["https://s3-media3.fl.yelpcdn.com/bphoto/DA3a1utmWOOTuuHTHgSZ9A/o.jpg", "https://s3-media3.fl.yelpcdn.com/bphoto/RBQJk83EkYYQRmqfd9pWxw/o.jpg", "https://s3-media2.fl.yelpcdn.com/bphoto/78wPfi5yB7ku85wC7R1R4Q/o.jpg"], "location": {"country": "US", "address2": "", "state": "NY", "city": "New York", "address1": "1501 Broadway", "zip_code": "10036", "address3": ""}}