{"term": "attractions", "name": "Cleopatra's Needle", "location": {"country": "US", "address2": "", "state": "NY", "city": "New York", "address1": "2485 Broadway", "zip_code": "10025", "address3": ""}, "id": "cleopatras-needle-new-york", "phone": "+12127696969", "hours": [{"is_open_now": false, "open": [{"start": "1530", "end": "0200", "is_overnight": true, "day": 0}, {"start": "1530", "end": "0200", "is_overnight": true, "day": 1}, {"start": "1530", "end": "0300", "is_overnight": true, "day": 2}, {"start": "1530", "end": "0300", "is_overnight": true, "day": 3}, {"start": "1530", "end": "0400", "is_overnight": true, "day": 4}, {"start": "1530", "end": "0400", "is_overnight": true, "day": 5}, {"start": "1500", "end": "0200", "is_overnight": true, "day": 6}], "hours_type": "REGULAR"}], "is_closed": false, "coordinates": {"latitude": 40.7924512, "longitude": -73.9736557}, "review_count": 146, "price": "$$", "rating": 3.0, "image_url": "https://s3-media1.fl.yelpcdn.com/bphoto/zJK9FfBZ5B649ihEmPnIIw/o.jpg", "url": "https://www.yelp.com/biz/cleopatras-needle-new-york?adjust_creative=92p07_JjKyriZTQxAXRiKQ&utm_campaign=yelp_api_v3&utm_medium=api_v3_business_lookup&utm_source=92p07_JjKyriZTQxAXRiKQ", "is_claimed": true, "categories": [{"alias": "jazzandblues", "title": "Jazz & Blues"}, {"alias": "mediterranean", "title": "Mediterranean"}, {"alias": "coffee", "title": "Coffee & Tea"}], "photos": ["https://s3-media4.fl.yelpcdn.com/bphoto/zJK9FfBZ5B649ihEmPnIIw/o.jpg", "https://s3-media2.fl.yelpcdn.com/bphoto/Y-BH6kPpmNNPx7nrsVwSKw/o.jpg", "https://s3-media1.fl.yelpcdn.com/bphoto/idlDoVRrsm9h55zv4F2ggg/o.jpg"]}