{"term": "restaurants", "name": "iJava Coffee & Eatery", "location": {"country": "US", "address2": null, "state": "CA", "city": "San Jose", "address1": "387 Delmas Ave", "zip_code": "95126", "address3": ""}, "id": "ijava-coffee-and-eatery-san-jose", "phone": "+14087539732", "hours": [{"is_open_now": false, "open": [{"start": "0630", "end": "1900", "is_overnight": false, "day": 0}, {"start": "0630", "end": "1900", "is_overnight": false, "day": 1}, {"start": "0630", "end": "1900", "is_overnight": false, "day": 2}, {"start": "0630", "end": "1900", "is_overnight": false, "day": 3}, {"start": "0630", "end": "1900", "is_overnight": false, "day": 4}, {"start": "0800", "end": "1800", "is_overnight": false, "day": 5}, {"start": "0800", "end": "1800", "is_overnight": false, "day": 6}], "hours_type": "REGULAR"}], "is_closed": false, "coordinates": {"latitude": 37.3261211279172, "longitude": -121.894719195483}, "review_count": 352, "price": "$", "rating": 4.0, "image_url": "https://s3-media3.fl.yelpcdn.com/bphoto/wsBv81fPVDHAyU5B_Y7jsQ/o.jpg", "url": "https://www.yelp.com/biz/ijava-coffee-and-eatery-san-jose?adjust_creative=92p07_JjKyriZTQxAXRiKQ&utm_campaign=yelp_api_v3&utm_medium=api_v3_business_lookup&utm_source=92p07_JjKyriZTQxAXRiKQ", "is_claimed": true, "categories": [{"alias": "cafes", "title": "Cafes"}, {"alias": "coffee", "title": "Coffee & Tea"}, {"alias": "breakfast_brunch", "title": "Breakfast & Brunch"}], "photos": ["https://s3-media3.fl.yelpcdn.com/bphoto/nLnvzoqiG5AwzAKqz_i0ug/o.jpg", "https://s3-media4.fl.yelpcdn.com/bphoto/bp-uyJopXZgs8mmMkSisYw/o.jpg", "https://s3-media4.fl.yelpcdn.com/bphoto/qN5UFeYgFpwJlNLQRQ_DWQ/o.jpg"]}