{"term": "restaurants", "name": "Sezar", "location": {"country": "AU", "address2": "", "state": "VIC", "city": "Melbourne", "address1": "6 Melbourne Pl", "zip_code": "3000", "address3": ""}, "id": "sezar-melbourne", "phone": "+61396639882", "hours": [{"is_open_now": false, "open": [{"start": "1200", "end": "1500", "is_overnight": false, "day": 0}, {"start": "1730", "end": "2300", "is_overnight": false, "day": 0}, {"start": "1200", "end": "1500", "is_overnight": false, "day": 1}, {"start": "1730", "end": "2300", "is_overnight": false, "day": 1}, {"start": "1200", "end": "1500", "is_overnight": false, "day": 2}, {"start": "1730", "end": "2300", "is_overnight": false, "day": 2}, {"start": "1200", "end": "1500", "is_overnight": false, "day": 3}, {"start": "1730", "end": "2300", "is_overnight": false, "day": 3}, {"start": "1200", "end": "1500", "is_overnight": false, "day": 4}, {"start": "1730", "end": "2300", "is_overnight": false, "day": 4}, {"start": "1730", "end": "2300", "is_overnight": false, "day": 5}], "hours_type": "REGULAR"}], "is_closed": false, "coordinates": {"latitude": -37.813483, "longitude": 144.968884}, "review_count": 15, "price": "$$$", "rating": 4.0, "image_url": "https://s3-media4.fl.yelpcdn.com/bphoto/9AerWmRAtLV66w8f_H8XLQ/o.jpg", "url": "https://www.yelp.com/biz/sezar-melbourne?adjust_creative=92p07_JjKyriZTQxAXRiKQ&utm_campaign=yelp_api_v3&utm_medium=api_v3_business_lookup&utm_source=92p07_JjKyriZTQxAXRiKQ", "is_claimed": false, "categories": [{"alias": "tapasmallplates", "title": "Tapas/Small Plates"}, {"alias": "mideastern", "title": "Middle Eastern"}], "photos": ["https://s3-media2.fl.yelpcdn.com/bphoto/9AerWmRAtLV66w8f_H8XLQ/o.jpg", "https://s3-media2.fl.yelpcdn.com/bphoto/gqRxshZpd1q0XuNS11jn8Q/o.jpg", "https://s3-media2.fl.yelpcdn.com/bphoto/VrtlYFzG975Qs8_wRBL1yg/o.jpg"]}