{"term": "attractions", "name": "S.Y Removals. Single Item to Full House Removals Services", "phone": "+447943398434", "id": "s-y-removals-single-item-to-full-house-removals-services-manchester", "hours": [{"is_open_now": true, "open": [{"start": "0800", "end": "0800", "is_overnight": true, "day": 0}, {"start": "0800", "end": "0800", "is_overnight": true, "day": 1}, {"start": "0800", "end": "0800", "is_overnight": true, "day": 2}, {"start": "0800", "end": "0800", "is_overnight": true, "day": 3}, {"start": "0800", "end": "0800", "is_overnight": true, "day": 4}, {"start": "0800", "end": "0800", "is_overnight": true, "day": 5}, {"start": "0800", "end": "0800", "is_overnight": true, "day": 6}], "hours_type": "REGULAR"}], "is_closed": false, "coordinates": {"latitude": 53.4580269, "longitude": -2.2474952}, "review_count": 1, "rating": 5.0, "image_url": "https://s3-media2.fl.yelpcdn.com/bphoto/1B-lWiK24SLT4uFD5Nm4AQ/o.jpg", "url": "https://www.yelp.com/biz/s-y-removals-single-item-to-full-house-removals-services-manchester?adjust_creative=92p07_JjKyriZTQxAXRiKQ&utm_campaign=yelp_api_v3&utm_medium=api_v3_business_lookup&utm_source=92p07_JjKyriZTQxAXRiKQ", "is_claimed": false, "categories": [{"alias": "publictransport", "title": "Public Transportation"}], "photos": ["https://s3-media2.fl.yelpcdn.com/bphoto/1B-lWiK24SLT4uFD5Nm4AQ/o.jpg", "https://s3-media2.fl.yelpcdn.com/bphoto/_CJNa0piS81cmq1PXc6vlw/o.jpg", "https://s3-media3.fl.yelpcdn.com/bphoto/pkby7ETY_4MU7oDJZSRLOg/o.jpg"], "location": {"country": "GB", "address2": "", "state": "XGM", "city": "Manchester", "address1": "4 Crosscliffe street", "zip_code": "M16 7DE", "address3": ""}}